LICENSE
MANIFEST.in
README.rst
setup.py
xsnippet_cli/__init__.py
xsnippet_cli/api.py
xsnippet_cli/cli.py
xsnippet_cli.egg-info/PKG-INFO
xsnippet_cli.egg-info/SOURCES.txt
xsnippet_cli.egg-info/dependency_links.txt
xsnippet_cli.egg-info/entry_points.txt
xsnippet_cli.egg-info/requires.txt
xsnippet_cli.egg-info/top_level.txt