Metadata-Version: 1.1
Name: xsnippet-cli
Version: 0.1.2
Summary: A simple command line interface for the XSnippet service.
Home-page: https://github.com/xsnippet/xsnippet-cli
Author: Igor Kalnitsky
Author-email: igor@kalnitsky.org
License: BSD License
Platform: UNKNOWN
Classifier: Environment :: Web Environment
Classifier: Intended Audience :: Developers
Classifier: License :: OSI Approved :: BSD License
Classifier: Programming Language :: Python
Classifier: Programming Language :: Python :: 2.7
Classifier: Programming Language :: Python :: 3
Classifier: Programming Language :: Python :: 3.2
Classifier: Programming Language :: Python :: 3.3
